wbclient/__init__.py
wbclient/main.py
wbclient/wb_commands.py
wbclient/wb_config.py
wbclient/wb_logfile.py
wbclient/wb_processes.py
wbclient/wb_server.py
wbclient-2.0.2.dist-info/licenses/LICENSE
wbclient-2.0.2.dist-info/METADATA
wbclient-2.0.2.dist-info/WHEEL
wbclient-2.0.2.dist-info/entry_points.txt
wbclient-2.0.2.dist-info/top_level.txt
wbclient-2.0.2.dist-info/RECORD
