Metadata-Version: 2.4
Name: wbclient
Version: 2.0.2
Summary: Monitor and control FileMaker Servers
Author-email: Peter Wagemans <twinge_sophism.04@icloud.com>, Ian Jempson <ianjempson@gmail.com>
License: <!DOCTYPE html>
Project-URL: Homepage, https://github.com/DataManixFM/WhistleBlower
Keywords: FileMaker,FileMaker Server,Monitor,Log
Classifier: License :: Freeware
Classifier: Programming Language :: Python
Classifier: Programming Language :: Python :: 3
Classifier: Topic :: System :: Monitoring
Classifier: Topic :: Database :: Database Engines/Servers
Requires-Python: >=3.9
License-File: LICENSE
Requires-Dist: keyboard>=0.13.5
Requires-Dist: urllib3>=2.2.1
Requires-Dist: pandas>=2.3.2
Requires-Dist: psutil>=7.0.0
Requires-Dist: python-fmrest>=1.7.5
Requires-Dist: urllib3>=2.2.1
Requires-Dist: appdirs~=1.4.4
Requires-Dist: pathlib~=1.0.1
Dynamic: license-file
